fuckoff/__init__.py
fuckoff/fuckoff.py
fuckoff-0.2.0.dist-info/METADATA
fuckoff-0.2.0.dist-info/WHEEL
fuckoff-0.2.0.dist-info/RECORD
